odoo/addons/account_payment_line_employee_wages/README.rst
odoo/addons/account_payment_line_employee_wages/__init__.py
odoo/addons/account_payment_line_employee_wages/__manifest__.py
odoo/addons/account_payment_line_employee_wages/models/__init__.py
odoo/addons/account_payment_line_employee_wages/models/account_move_line.py
odoo/addons/account_payment_line_employee_wages/static/description/icon.png
odoo/addons/account_payment_line_employee_wages/tests/__init__.py
odoo/addons/account_payment_line_employee_wages/tests/test_account_move_line.py
odoo12_addon_account_payment_line_employee_wages-12.0.1.0.0.dist-info/METADATA
odoo12_addon_account_payment_line_employee_wages-12.0.1.0.0.dist-info/WHEEL
odoo12_addon_account_payment_line_employee_wages-12.0.1.0.0.dist-info/top_level.txt
odoo12_addon_account_payment_line_employee_wages-12.0.1.0.0.dist-info/RECORD
