Metadata-Version: 2.1
Name: odoo12-addon-account-payment-line-employee-wages
Version: 12.0.1.0.0
Summary: When creating an account_payment_line, chose by default an employee's bank account if the selected partner is also an employee and the payment is part of its wage.
Home-page: https://gitlab.com/somitcoop/erp-research/odoo-accounting
Author: Som It Cooperatiu SCCL, Som Connexió SCCL, Odoo Community Association (OCA)
Author-email: support@odoo-community.org
License: AGPL-3
Platform: UNKNOWN
Classifier: Programming Language :: Python
Classifier: Framework :: Odoo
Classifier: Framework :: Odoo :: 12.0
Classifier: License :: OSI Approved :: GNU Affero General Public License v3
Requires-Python: >=3.5
Requires-Dist: odoo12-addon-account-payment-order
Requires-Dist: odoo<12.1dev,>=12.0a
